pyroza/__init__.py
pyroza/version.py
pyroza/pyroza/__init__.py
pyroza/pyroza/load.py
pyroza/pyroza/log.py
pyroza/pyroza/utils/PyroHelpers.py
pyroza/pyroza/utils/__init__.py
pyroza/pyroza/utils/adminHelpers.py
pyroza/pyroza/utils/ai.py
pyroza/pyroza/utils/aiohttp_helper.py
pyroza/pyroza/utils/basic.py
pyroza/pyroza/utils/constants.py
pyroza/pyroza/utils/function.py
pyroza/pyroza/utils/get_id.py
pyroza/pyroza/utils/http.py
pyroza/pyroza/utils/inline.py
pyroza/pyroza/utils/interval.py
pyroza/pyroza/utils/misc.py
pyroza/pyroza/utils/parser.py
pyroza/pyroza/utils/pilter.py
pyroza/pyroza/utils/tools.py
pyroza/pyroza/utils/unpack.py
pyroza/pyroza/utils/utility.py
pyroza/pyroza/utils/db/__init__.py
pyroza/pyroza/utils/db/permit.py
pyroza-1.9.2.dist-info/LICENSE
pyroza-1.9.2.dist-info/METADATA
pyroza-1.9.2.dist-info/WHEEL
pyroza-1.9.2.dist-info/top_level.txt
pyroza-1.9.2.dist-info/RECORD
