Metadata-Version: 2.1
Name: pyroza
Version: 1.9.2
Summary: A Secure and Powerful Python-Pyrogram Based Library For Zaa-Pyro.
Home-page: https://github.com/pinxrobtik/pyroza
Author: naya1503
Author-email: cosmospanas70@gmail.com
License: GNU AFFERO GENERAL PUBLIC LICENSE (v3)
Project-URL: Bug Tracker, https://github.com/pinxrobtik/pyroza/issues
Project-URL: Documentation, https://t.me/kynansupport
Project-URL: Source Code, https://github.com/pinxrobtik/pyroza
Platform: UNKNOWN
Classifier: Programming Language :: Python :: 3
Classifier: Programming Language :: Python :: 3.8
Classifier: Programming Language :: Python :: 3.9
Classifier: Programming Language :: Python :: 3.10
Classifier: Programming Language :: Python :: 3.11
Classifier: Programming Language :: Python :: 3.12
Classifier: License :: OSI Approved :: GNU General Public License v3 (GPLv3)
Classifier: Operating System :: OS Independent
Requires-Python: >3.7, <3.12
License-File: LICENSE
Requires-Dist: aiosqlite (<0.18.0,>=0.16.0)
Requires-Dist: pyaes (==1.6.1)
Requires-Dist: pysocks (==1.7.1)
Requires-Dist: pytgcalls (==3.0.0.dev24)
Requires-Dist: pytz
Requires-Dist: tgcrypto
